fastapi_gateway_auto_generate/Config.py
fastapi_gateway_auto_generate/Generator.py
fastapi_gateway_auto_generate/__init__.py
fastapi_gateway_auto_generate/alembic.ini
fastapi_gateway_auto_generate/database/AddService.py
fastapi_gateway_auto_generate/database/DeleteService.py
fastapi_gateway_auto_generate/database/Errors.py
fastapi_gateway_auto_generate/database/GetAllServices.py
fastapi_gateway_auto_generate/database/SQLAlchemy/__init__.py
fastapi_gateway_auto_generate/database/SQLAlchemy/declarative_base.py
fastapi_gateway_auto_generate/database/SetMarkDeleteSerivce.py
fastapi_gateway_auto_generate/database/StatusService.py
fastapi_gateway_auto_generate/database/UrlService.py
fastapi_gateway_auto_generate/database/__init__.py
fastapi_gateway_auto_generate/database/models/Services.py
fastapi_gateway_auto_generate/database/models/StatusServices.py
fastapi_gateway_auto_generate/database/models/UrlServices.py
fastapi_gateway_auto_generate/database/models/__init__.py
fastapi_gateway_auto_generate/domain/__init__.py
fastapi_gateway_auto_generate/domain/models/RouteModel.py
fastapi_gateway_auto_generate/domain/models/__init__.py
fastapi_gateway_auto_generate/domain/usecases/BuildRouteModelsUsecase.py
fastapi_gateway_auto_generate/domain/usecases/BuildRoutesUsecase.py
fastapi_gateway_auto_generate/domain/usecases/DeleteTmpModelsFilesUsecase.py
fastapi_gateway_auto_generate/domain/usecases/DeletingExistingRoutesUsecase.py
fastapi_gateway_auto_generate/domain/usecases/InitDatabaseUsecase.py
fastapi_gateway_auto_generate/domain/usecases/RefreshServicesUsecase.py
fastapi_gateway_auto_generate/domain/usecases/UpdateOpenApiSchemaUsecase.py
fastapi_gateway_auto_generate/domain/usecases/__init__.py
fastapi_gateway_auto_generate/exceptions/ConfigException.py
fastapi_gateway_auto_generate/exceptions/FastapiGatewayAutoGenerageException.py
fastapi_gateway_auto_generate/exceptions/__init__.py
fastapi_gateway_auto_generate/management/Management.py
fastapi_gateway_auto_generate-0.3.1.dist-info/LICENSE
fastapi_gateway_auto_generate-0.3.1.dist-info/METADATA
fastapi_gateway_auto_generate-0.3.1.dist-info/WHEEL
fastapi_gateway_auto_generate-0.3.1.dist-info/RECORD
