Metadata-Version: 2.1
Name: fastapi-gateway-auto-generate
Version: 0.3.1
Summary: This library allows you to automatically generate requests for the API Gateway.
Home-page: https://github.com/xitowzys-ISZF/FastAPI-Auto-Generate-Gateway
License: MIT
Keywords: python,fastapi,gateway,api,microservice,microservices
Author: Kalinka George
Author-email: xitowzys@gmail.com
Requires-Python: >=3.11,<4.0
Classifier: License :: OSI Approved :: MIT License
Classifier: Programming Language :: Python :: 3
Classifier: Programming Language :: Python :: 3.11
Requires-Dist: alembic (>=1.8.1,<2.0.0)
Requires-Dist: datamodel-code-generator (>=0.14.0,<0.15.0)
Requires-Dist: fastapi (>=0.88.0,<0.89.0)
Requires-Dist: fastapi-gateway-ultra (>=0.1.1,<0.2.0)
Requires-Dist: fastapi-openapi-parser (>=1.0.1,<2.0.0)
Requires-Dist: loguru (>=0.7.0,<0.8.0)
Requires-Dist: makefun (>=1.15.0,<2.0.0)
Requires-Dist: python-multipart (>=0.0.5,<0.0.6)
Requires-Dist: rich (>=13.3.2,<14.0.0)
Requires-Dist: shortuuid (>=1.0.11,<2.0.0)
Requires-Dist: sqlalchemy (>=1.4.44,<2.0.0)
Requires-Dist: validators (>=0.20.0,<0.21.0)
Project-URL: Repository, https://github.com/xitowzys-ISZF/FastAPI-Auto-Generate-Gateway
